{
    "id": "U13",
    "name_en": "Imperial Striker",
    "name_jp": "帝国精鋭先鋒",
    "name_cn": "帝国前锋精锐",
    "atk_type_jp": "近・物理",
    "hp": "12000",
    "atk": "900",
    "def": "800",
    "res": "50",
    "aspd%": "100",
    "aspd": "4.5",
    "range": "1.5",
    
    "weight": "4",
    "スタン耐性": "無",
    "眠り耐性": "無",
    "凍結耐性": "",
    "lifepoint":1,"ms": "0.7",
    "type_jp": [
        "遠距離",
        "精鋭"
    ],
    "type_en": [
        "Ranged"
    ],
    "type_cn": [
        "远程"
    ],
    "special": ""
}